remote_pdb.py
remote_pdb-2.0.0.dist-info/AUTHORS.rst
remote_pdb-2.0.0.dist-info/LICENSE
remote_pdb-2.0.0.dist-info/METADATA
remote_pdb-2.0.0.dist-info/WHEEL
remote_pdb-2.0.0.dist-info/top_level.txt
remote_pdb-2.0.0.dist-info/RECORD
