Metadata-Version: 1.2
Name: remote-pdb
Version: 2.0.0
Summary: Remote vanilla PDB (over TCP sockets) *done right*: no extras, proper handling around connection failures and CI. Based on `pdbx <https://pypi.python.org/pypi/pdbx>`_.
Home-page: https://github.com/ionelmc/python-remote-pdb
Author: Ionel Cristian Mărieș
Author-email: contact@ionelmc.ro
License: BSD 2-Clause License
Project-URL: Documentation, https://python-remote-pdb.readthedocs.io/
Project-URL: Changelog, https://python-remote-pdb.readthedocs.io/en/latest/changelog.html
Project-URL: Issue Tracker, https://github.com/ionelmc/python-remote-pdb/issues
Platform: UNKNOWN
Classifier: Development Status :: 5 - Production/Stable
Classifier: Intended Audience :: Developers
Classifier: License :: OSI Approved :: BSD License
Classifier: Operating System :: Unix
Classifier: Operating System :: POSIX
Classifier: Operating System :: Microsoft :: Windows
Classifier: Programming Language :: Python
Classifier: Programming Language :: Python :: 2.7
Classifier: Programming Language :: Python :: 3
Classifier: Programming Language :: Python :: 3.5
Classifier: Programming Language :: Python :: 3.6
Classifier: Programming Language :: Python :: 3.7
Classifier: Programming Language :: Python :: Implementation :: CPython
Classifier: Programming Language :: Python :: Implementation :: PyPy
Classifier: Topic :: Utilities
Requires-Python: >=2.7, !=3.0.*, !=3.1.*, !=3.2.*, !=3.3.*, !=3.4.*
